bbstat/__init__.py
bbstat/_version.py
bbstat/bootstrap.py
bbstat/evaluate.py
bbstat/plot.py
bbstat/registry.py
bbstat/resample.py
bbstat/statistics.py
bbstat/utils.py
bbstat-0.1.1.dist-info/licenses/LICENSE
bbstat-0.1.1.dist-info/METADATA
bbstat-0.1.1.dist-info/WHEEL
bbstat-0.1.1.dist-info/top_level.txt
bbstat-0.1.1.dist-info/RECORD
