Metadata-Version: 2.4
Name: bbstat
Version: 0.1.1
Summary: A lightweight library for Bayesian bootstrapping and statistical evaluation.
Author-email: Chris Wehmeyer <wehmeyer.chris@gmail.com>
License-Expression: MIT
Project-URL: Homepage, https://github.com/cwehmeyer/bbstat
Project-URL: Documentation, https://cwehmeyer.github.io/bbstat/
Project-URL: Repository, https://github.com/cwehmeyer/bbstat.git
Project-URL: Issues, https://github.com/cwehmeyer/bbstat/issues
Project-URL: Changelog, https://github.com/cwehmeyer/bbstat/blob/main/CHANGELOG.md
Keywords: bayesian,bootstrap,statistics
Classifier: Development Status :: 3 - Alpha
Classifier: Programming Language :: Python :: 3
Classifier: Operating System :: OS Independent
Requires-Python: >=3.10
License-File: LICENSE
Requires-Dist: matplotlib
Requires-Dist: numpy>=1.21
Requires-Dist: scipy>=1.11
Provides-Extra: test
Requires-Dist: pytest>=7.0; extra == "test"
Requires-Dist: pytest-cov; extra == "test"
Provides-Extra: docs
Requires-Dist: mkdocs; extra == "docs"
Requires-Dist: mkdocs-autorefs; extra == "docs"
Requires-Dist: mkdocs-get-deps; extra == "docs"
Requires-Dist: mkdocs-include-markdown-plugin; extra == "docs"
Requires-Dist: mkdocstrings[python]; extra == "docs"
Provides-Extra: lint
Requires-Dist: black; extra == "lint"
Requires-Dist: ruff; extra == "lint"
Provides-Extra: typecheck
Requires-Dist: mypy; extra == "typecheck"
Requires-Dist: scipy-stubs; extra == "typecheck"
Provides-Extra: dev
Requires-Dist: build; extra == "dev"
Requires-Dist: pre-commit; extra == "dev"
Requires-Dist: tox; extra == "dev"
Requires-Dist: twine; extra == "dev"
Dynamic: license-file
